tarea3/__init__.py
tarea3/principal.py
tarea3/Control/__init__.py
tarea3/Control/basedatos.py
tarea3/Control/mostrar_reservas.py
tarea3/Control/reservar.py
tarea3/Modelo/__init__.py
tarea3/Modelo/reservas.db
tarea3/Modelo/reservas.sql
tarea3/Recursos/__init__.py
tarea3/Recursos/img/brianda.jpeg
tarea3/Recursos/img/brianda1.png
tarea3/Vistas/__init__.py
tarea3/Vistas/frmMainMenu.ui
tarea3/Vistas/frmMostrarReservas.ui
tarea3/Vistas/frmReservas.ui
tarea3/Vistas/ui_frmMainMenu.py
tarea3/Vistas/ui_frmMostrarReservas.py
tarea3/Vistas/ui_frmReservas.py
tarea4_ASG-0.1.0.dist-info/METADATA
tarea4_ASG-0.1.0.dist-info/WHEEL
tarea4_ASG-0.1.0.dist-info/entry_points.txt
tarea4_ASG-0.1.0.dist-info/top_level.txt
tarea4_ASG-0.1.0.dist-info/RECORD
